registration/__init__.py
registration/admin.py
registration/auth_urls.py
registration/forms.py
registration/models.py
registration/signals.py
registration/users.py
registration/utils.py
registration/views.py
registration/backends/__init__.py
registration/backends/admin_approval/__init__.py
registration/backends/admin_approval/urls.py
registration/backends/admin_approval/views.py
registration/backends/default/__init__.py
registration/backends/default/urls.py
registration/backends/default/views.py
registration/backends/simple/__init__.py
registration/backends/simple/urls.py
registration/backends/simple/views.py
registration/locale/ar/LC_MESSAGES/django.mo
registration/locale/ar/LC_MESSAGES/django.po
registration/locale/bg/LC_MESSAGES/django.mo
registration/locale/bg/LC_MESSAGES/django.po
registration/locale/ca/LC_MESSAGES/django.mo
registration/locale/ca/LC_MESSAGES/django.po
registration/locale/cs/LC_MESSAGES/django.mo
registration/locale/cs/LC_MESSAGES/django.po
registration/locale/da/LC_MESSAGES/django.mo
registration/locale/da/LC_MESSAGES/django.po
registration/locale/de/LC_MESSAGES/django.mo
registration/locale/de/LC_MESSAGES/django.po
registration/locale/el/LC_MESSAGES/django.mo
registration/locale/el/LC_MESSAGES/django.po
registration/locale/en/LC_MESSAGES/django.mo
registration/locale/en/LC_MESSAGES/django.po
registration/locale/es/LC_MESSAGES/django.mo
registration/locale/es/LC_MESSAGES/django.po
registration/locale/es_AR/LC_MESSAGES/django.mo
registration/locale/es_AR/LC_MESSAGES/django.po
registration/locale/fa/LC_MESSAGES/django.mo
registration/locale/fa/LC_MESSAGES/django.po
registration/locale/fr/LC_MESSAGES/django.mo
registration/locale/fr/LC_MESSAGES/django.po
registration/locale/he/LC_MESSAGES/django.mo
registration/locale/he/LC_MESSAGES/django.po
registration/locale/hr/LC_MESSAGES/django.mo
registration/locale/hr/LC_MESSAGES/django.po
registration/locale/hu/LC_MESSAGES/django.mo
registration/locale/hu/LC_MESSAGES/django.po
django_registration_redux-2.10.dist-info/AUTHORS
django_registration_redux-2.10.dist-info/LICENSE
django_registration_redux-2.10.dist-info/METADATA
django_registration_redux-2.10.dist-info/WHEEL
django_registration_redux-2.10.dist-info/top_level.txt
django_registration_redux-2.10.dist-info/RECORD
